yotpy/__init__.py
yotpy/core.py
yotpy/exceptions.py
yotpy-0.0.91.dist-info/LICENSE
yotpy-0.0.91.dist-info/WHEEL
yotpy-0.0.91.dist-info/METADATA
yotpy-0.0.91.dist-info/RECORD
