Metadata-Version: 2.1
Name: yotpy
Version: 0.0.91
Summary: Yotpy: An easy-to-use Python wrapper for the Yotpo web API.
Home-page: https://github.com/wlk-dev/yotpy
License: MIT
Keywords: yotpo, api, wrapper, python, data, transformation, client, integration, review, ecommerce
Author: William Koelling
Author-email: william.koelling@gmail.com
Classifier: Development Status :: 3 - Alpha
Classifier: License :: OSI Approved :: MIT License
Classifier: Programming Language :: Python :: 3
Classifier: Programming Language :: Python :: 3.9
Classifier: Programming Language :: Python :: 3.11
Requires-Dist: aiohttp
Requires-Dist: requests
Requires-Dist: openpyxl
Project-URL: Documentation, https://wlk-dev.github.io/yotpy/yotpy.html
